Workbook

Sheet Workflow

Sheet Calculator Form
A1: Target Costing Calculator
A2: Enter inputs from top to bottom. Yellow cells are user inputs. Competitor comparison is used only in Beat competition mode.
A3: Group
A4: Division
A5: Business Unit
A6: Product Family
A7: Product Name
A8: Program Name
A11: 1) Program Goal, Competitive Context, and Price Basis
A12: Goal type | B12: Beat competition or improve margin on an existing product | C12: Beat competition
A13: Competition ASP (best estimate) | B13: Competitor selling price / net ASP estimate used for market context | C13: 5000
A14: Competition COGS (best estimate) | B14: Best estimate of competitor unit cost; used for comparison only in Beat competition mode | C14: 2500
A15: Current list ASP | B15: Your current list ASP before discounts / rebates | C15: 8000
A16: Avg discount % | B16: Average discount vs list | C16: 0.05
A17: Avg rebate / promo % | B17: Average rebate / promo leakage | C17: 0
A18: Avg credits / other % | B18: Any additional price leakage | C18: 0
A19: Current Net ASP | B19: Your realized current net ASP after the price waterfall | C19: =C15*(1-C16-C17-C18) -> 7600
A20: Planned ASP change % (margin improvement case) | B20: Used only if goal = Margin improvement | C20: 0
A21: Target selling price used | B21: Beat competition = competition ASP. Margin improvement = current net ASP plus planned ASP change | C21: =IF(C12="Beat competition",C13,C19*(1+C20)) -> 5000
A22: Corporate margin type | B22: GM for existing business model; OM if SG&A / service burden changes materially | C22: GM
A23: Corporate target margin % | B23: Single target margin input | C23: 0.5
A24: SG&A per unit (OM only) | B24: Required only if OM is selected | C24: 0
A25: Target profit / unit | B25: Target margin dollars at target selling price | C25: =C21*C23 -> 2500
A26: Allowable target COGS before buffer | B26: Target cost ceiling before risk buffer | C26: =IF(C22="GM",C21*(1-C23),C21*(1-C23)-C24) -> 2500
A27: Risk buffer % | B27: Execution buffer | C27: 0.02
A28: Final allowable target COGS | B28: Target COGS ceiling after buffer | C28: =C26*(1-C27) -> 2450
A31: 2) Baseline Current Product COGS Split
A32: BOM | B32: Current BOM cost per unit | C32: 2300
A33: Direct Labor | B33: Current direct labor cost per unit | C33: 1000
A34: Variable OH | B34: Current variable overhead per unit | C34: 250
A35: Fixed OH | B35: Current fixed overhead per unit | C35: 700
A36: Freight / Duty | B36: Current logistics, duty, inbound / outbound per unit | C36: 150
A37: Other | B37: Other current COGS items per unit | C37: 10 | E37: Install/Warranty
A38: Other | B38: Other current COGS items per unit | C38: 0
A39: Baseline Total COGS | B39: Current total COGS structure | C39: =SUM(C32:C38) -> 4410
A42: 2A) Baseline Should Cost Split
A43: BOM Should Cost | B43: Baseline should-cost BOM per unit | C43: 1700
A44: Direct Labor Should Cost | B44: Baseline should-cost direct labor per unit | C44: 750
A45: Variable OH Should Cost | B45: Baseline should-cost variable OH per unit | C45: 150
A46: Fixed OH Should Cost | B46: Baseline should-cost fixed OH per unit | C46: 700
A47: Freight / Duty Should Cost | B47: Baseline should-cost freight / duty per unit | C47: 100
A48: =A37 -> Other | B48: =B37 -> Other current COGS items per unit | C48: 10
A49: =A38 -> Other | B49: =B38 -> Other current COGS items per unit | C49: 0
A50: Baseline Total Should Cost | B50: Total baseline should-cost structure | C50: =SUM(C43:C49) -> 3410
A52: 3) Desired COGS Reduction by Cost Element (%)
A53: Cost element | B53: Reduction % | C53: Target cost / unit
A54: =A32 -> BOM | B54: 0.15 | C54: =C32*(1-B54) -> 1955
A55: =A33 -> Direct Labor | B55: 0.05 | C55: =C33*(1-B55) -> 950
A56: =A34 -> Variable OH | B56: 0 | C56: =C34*(1-B56) -> 250
A57: =A35 -> Fixed OH | B57: 0 | C57: =C35*(1-B57) -> 700
A58: =A36 -> Freight / Duty | B58: 0.1 | C58: =C36*(1-B58) -> 135
A59: =A37 -> Other | B59: 0 | C59: =C37*(1-B59) -> 10
A60: =A38 -> Other | B60: 0 | C60: =C38*(1-B60) -> 0
A61: Feasible target COGS from category reductions | C61: =SUM(C54:C60) -> 4000
A64: 4) Executive Decision Dashboard
A66: Cost Position | D66: Gap Analysis
A67: Baseline COGS | C67: =C39 -> 4410 | D67: Gap vs Target | F67: =C70-C69 -> -1550
A68: Should Cost Baseline | C68: =C50 -> 3410 | D68: Gap vs Should | F68: =C68-C69 -> -590
A69: Feasible COGS | C69: =C61 -> 4000 | D69: Structural Gap | F69: =C68-C67 -> -1000
A70: Target COGS | C70: =C28 -> 2450 | D70: Strategic Gap | F70: =C70-C68 -> -960
A72: Profit Check | D72: Action Closure
A73: Achieved GM | C73: =IFERROR((C21-C61)/C21,"") -> 0.2 | D73: Required Cost Down | F73: =MAX(0,C61-C28) -> 1550
A74: Achieved OM | C74: =IFERROR((C21-C61-C24)/C21,"") -> 0.2 | D74: Identified Savings | F74: ='Action Tracker'!K56 -> 336.5
D75: Applied Savings | F75: =MIN(F73,F74) -> 336.5
D76: Remaining Gap | F76: =MAX(0,F73-F75) -> 1213.5
A78: Decision
A79: Status | C79: =IF(C12="Beat competition",IF(AND(F67<=0,C69<=C14),"GREEN",IF(OR(F67<=0,C69<=C14),"YELLOW","RED")),IF(C22="GM",IF(C73>=C23,"GREEN",IF(C23-C73<=0.02,"YELLOW","RED")),IF(C74>=C23,"GREEN",IF(C23-C74<=0.02,"YELLOW","RED")))) -> YELLOW
A80: Interpretation | C80: =IF(C79="GREEN","Meets target logic",IF(C79="YELLOW","Near target / partial pass","Gap remains")) -> Near target / partial pass
A81: Target Feasibility Flag | C81: =IF(C68>C70,"UNREALISTIC TARGET",IF(C69>C68,"EXECUTION GAP","ON TRACK")) -> UNREALISTIC TARGET

Sheet Sensitivity
A1: Sensitivity
A3: Base target selling price | B3: ='Calculator Form'!C21 -> 5000 | H3: Logic note
A4: Base target margin % | B4: ='Calculator Form'!C23 -> 0.5 | H4: Table 1 = allowable target COGS sensitivity to ASP and target margin.
A5: Margin type | B5: ='Calculator Form'!C22 -> GM | H5: Table 2 = feasible COGS sensitivity to volume through fixed OH absorption.
A6: SG&A / unit | B6: ='Calculator Form'!C24 -> 0 | H6: Beat competition mode also shows gap vs competitor COGS.
A7: Baseline annual volume | B7: 10000
A8: Target fixed OH / unit | B8: ='Calculator Form'!C35 -> 700
A9: Competitor COGS (context) | B9: =IF('Calculator Form'!C12="Beat competition",'Calculator Form'!C14,"") -> 2500
A11: Allowable target COGS by ASP x Margin
A12: ASP Δ | B12: =B4+(-0.1) -> 0.4 | C12: =B4+(-0.05) -> 0.45 | D12: =B4 -> 0.5 | E12: =B4+(0.05) -> 0.55 | F12: =B4+(0.1) -> 0.6
A13: -0.1 | B13: =IF($B$5="GM",($B$3*(1+$A13))*(1-B$12),($B$3*(1+$A13))*(1-B$12)-$B$6) -> 2700 | C13: =IF($B$5="GM",($B$3*(1+$A13))*(1-C$12),($B$3*(1+$A13))*(1-C$12)-$B$6) -> 2475 | D13: =IF($B$5="GM",($B$3*(1+$A13))*(1-D$12),($B$3*(1+$A13))*(1-D$12)-$B$6) -> 2250 | E13: =IF($B$5="GM",($B$3*(1+$A13))*(1-E$12),($B$3*(1+$A13))*(1-E$12)-$B$6) -> 2025 | F13: =IF($B$5="GM",($B$3*(1+$A13))*(1-F$12),($B$3*(1+$A13))*(1-F$12)-$B$6) -> 1800
A14: -0.05 | B14: =IF($B$5="GM",($B$3*(1+$A14))*(1-B$12),($B$3*(1+$A14))*(1-B$12)-$B$6) -> 2850 | C14: =IF($B$5="GM",($B$3*(1+$A14))*(1-C$12),($B$3*(1+$A14))*(1-C$12)-$B$6) -> 2612.5 | D14: =IF($B$5="GM",($B$3*(1+$A14))*(1-D$12),($B$3*(1+$A14))*(1-D$12)-$B$6) -> 2375 | E14: =IF($B$5="GM",($B$3*(1+$A14))*(1-E$12),($B$3*(1+$A14))*(1-E$12)-$B$6) -> 2137.5 | F14: =IF($B$5="GM",($B$3*(1+$A14))*(1-F$12),($B$3*(1+$A14))*(1-F$12)-$B$6) -> 1900
A15: 0 | B15: =IF($B$5="GM",($B$3*(1+$A15))*(1-B$12),($B$3*(1+$A15))*(1-B$12)-$B$6) -> 3000 | C15: =IF($B$5="GM",($B$3*(1+$A15))*(1-C$12),($B$3*(1+$A15))*(1-C$12)-$B$6) -> 2750 | D15: =IF($B$5="GM",($B$3*(1+$A15))*(1-D$12),($B$3*(1+$A15))*(1-D$12)-$B$6) -> 2500 | E15: =IF($B$5="GM",($B$3*(1+$A15))*(1-E$12),($B$3*(1+$A15))*(1-E$12)-$B$6) -> 2250 | F15: =IF($B$5="GM",($B$3*(1+$A15))*(1-F$12),($B$3*(1+$A15))*(1-F$12)-$B$6) -> 2000
A16: 0.05 | B16: =IF($B$5="GM",($B$3*(1+$A16))*(1-B$12),($B$3*(1+$A16))*(1-B$12)-$B$6) -> 3150 | C16: =IF($B$5="GM",($B$3*(1+$A16))*(1-C$12),($B$3*(1+$A16))*(1-C$12)-$B$6) -> 2887.5 | D16: =IF($B$5="GM",($B$3*(1+$A16))*(1-D$12),($B$3*(1+$A16))*(1-D$12)-$B$6) -> 2625 | E16: =IF($B$5="GM",($B$3*(1+$A16))*(1-E$12),($B$3*(1+$A16))*(1-E$12)-$B$6) -> 2362.5 | F16: =IF($B$5="GM",($B$3*(1+$A16))*(1-F$12),($B$3*(1+$A16))*(1-F$12)-$B$6) -> 2100
A17: 0.1 | B17: =IF($B$5="GM",($B$3*(1+$A17))*(1-B$12),($B$3*(1+$A17))*(1-B$12)-$B$6) -> 3300 | C17: =IF($B$5="GM",($B$3*(1+$A17))*(1-C$12),($B$3*(1+$A17))*(1-C$12)-$B$6) -> 3025 | D17: =IF($B$5="GM",($B$3*(1+$A17))*(1-D$12),($B$3*(1+$A17))*(1-D$12)-$B$6) -> 2750 | E17: =IF($B$5="GM",($B$3*(1+$A17))*(1-E$12),($B$3*(1+$A17))*(1-E$12)-$B$6) -> 2475 | F17: =IF($B$5="GM",($B$3*(1+$A17))*(1-F$12),($B$3*(1+$A17))*(1-F$12)-$B$6) -> 2200
A19: Feasible COGS and Gap by Volume (fixed OH effect)
A20: Metric / Volume | B20: 5000 | C20: 7500 | D20: 10000 | E20: 15000 | F20: 20000
A21: Feasible COGS with volume-adjusted fixed OH | B21: ='Calculator Form'!C52-'Calculator Form'!C35+(IF(B$20=0,0,($B$7*$B$8)/B$20)) -> 700 | C21: ='Calculator Form'!C52-'Calculator Form'!C35+(IF(C$20=0,0,($B$7*$B$8)/C$20)) -> 233.33333 | D21: ='Calculator Form'!C52-'Calculator Form'!C35+(IF(D$20=0,0,($B$7*$B$8)/D$20)) -> 0 | E21: ='Calculator Form'!C52-'Calculator Form'!C35+(IF(E$20=0,0,($B$7*$B$8)/E$20)) -> -233.33333 | F21: ='Calculator Form'!C52-'Calculator Form'!C35+(IF(F$20=0,0,($B$7*$B$8)/F$20)) -> -350
A22: Gap vs allowable target | B22: =B21-'Calculator Form'!C28 -> -1750 | C22: =C21-'Calculator Form'!C28 -> -2216.6667 | D22: =D21-'Calculator Form'!C28 -> -2450 | E22: =E21-'Calculator Form'!C28 -> -2683.3333 | F22: =F21-'Calculator Form'!C28 -> -2800
A23: Gap vs competitor COGS (Beat competition only) | B23: =IF('Calculator Form'!C12="Beat competition",B21-$B$9,"") -> -1800 | C23: =IF('Calculator Form'!C12="Beat competition",C21-$B$9,"") -> -2266.6667 | D23: =IF('Calculator Form'!C12="Beat competition",D21-$B$9,"") -> -2500 | E23: =IF('Calculator Form'!C12="Beat competition",E21-$B$9,"") -> -2733.3333 | F23: =IF('Calculator Form'!C12="Beat competition",F21-$B$9,"") -> -2850

Sheet Action Tracker
A1: Action Tracker – Gap Closure Plan
A3: Delta reduction required | B3: =MAX(0,'Calculator Form'!F73) -> 1550 | D3: Savings identified so far | E3: =K56 -> 336.5 | G3: Remaining gap | H3: =MAX(0,B3-MIN(B3,E3)) -> 1213.5 | I3: Applied savings capped at gap | J3: =MIN(B3,E3) -> 336.5
A5: # | B5: Action | C5: Owner | D5: Subsystem | E5: Cost bucket | F5: Commitment | G5: Timing | H5: Maturity level | I5: Savings $/unit | J5: Probability % | K5: Weighted savings | M5: Maturity guide
A6: 1 | B6: Action 1 | C6: R&D | D6: Subsystem 1 | E6: BOM | F6: Opportunity | G6: Q4 | H6: Scoping | I6: 100 | J6: 0.5 | K6: =I6*J6 -> 50 | M6: Idea = concept only
A7: 2 | B7: Action 2 | C7: R&D | D7: Subsystem 2 | E7: BOM | F7: Opportunity | G7: Q4 | H7: Idea | I7: 20 | J7: 0.5 | K7: =I7*J7 -> 10 | M7: Scoping = under study
A8: 3 | B8: Action 3 | C8: R&D | D8: Subsystem 3 | E8: BOM | F8: Opportunity | G8: Q4 | H8: Validated | I8: 15 | J8: 0.7 | K8: =I8*J8 -> 10.5 | M8: Validated = technically validated
A9: 4 | B9: Action 4 | C9: Ops | D9: Assembly | E9: Direct Labor | F9: Opportunity | G9: Q4 | H9: Committed | I9: 20 | J9: 0.8 | K9: =I9*J9 -> 16 | M9: Committed = approved for execution
A10: 5 | B10: Action 5 | C10: Ops | D10: Assembly | E10: Direct Labor | F10: Opportunity | G10: Q4 | H10: Implemented | I10: 250 | J10: 1 | K10: =I10*J10 -> 250 | M10: Implemented = already landed
A11: 6 | H11: Idea | I11: 0 | J11: 1 | K11: =I11*J11 -> 0
A12: 7 | H12: Idea | I12: 0 | J12: 1 | K12: =I12*J12 -> 0
A13: 8 | H13: Idea | I13: 0 | J13: 1 | K13: =I13*J13 -> 0
A14: 9 | H14: Idea | I14: 0 | J14: 1 | K14: =I14*J14 -> 0
A15: 10 | H15: Idea | I15: 0 | J15: 1 | K15: =I15*J15 -> 0
A16: 11 | H16: Idea | I16: 0 | J16: 1 | K16: =I16*J16 -> 0
A17: 12 | H17: Idea | I17: 0 | J17: 1 | K17: =I17*J17 -> 0
A18: 13 | H18: Idea | I18: 0 | J18: 1 | K18: =I18*J18 -> 0
A19: 14 | H19: Idea | I19: 0 | J19: 1 | K19: =I19*J19 -> 0
A20: 15 | H20: Idea | I20: 0 | J20: 1 | K20: =I20*J20 -> 0
A21: 16 | H21: Idea | I21: 0 | J21: 1 | K21: =I21*J21 -> 0
A22: 17 | H22: Idea | I22: 0 | J22: 1 | K22: =I22*J22 -> 0
... A53: 48 | H53: Idea | I53: 0 | J53: 1 | K53: =I53*J53 -> 0
J54: Committed savings total | K54: =SUMIFS(I6:I55,F6:F55,"Committed") -> 0
J55: Opportunity weighted savings total | K55: =SUMIFS(K6:K55,F6:F55,"Opportunity") -> 336.5
J56: Total expected savings | K56: =K54+K55 -> 336.5

Sheet Read Me
A1: Read Me
A3: What changed in this version
A4: This version is organized as a simple form with linear inputs and no subsystem BOM section.
A5: 1) Program goal, competitive context, and price basis
A6: 2) Baseline current product COGS split
A7: 3) Desired cost reduction by cost element
A8: 4) Decision dashboard + linked action tracker
A9: 5) Goal-specific waterfall view
A11: Beat competition | B11: Target selling price used | C11: Competition ASP. Compare target COGS to competitor COGS and allowable target COGS.
A12: Margin improvement | B12: Target selling price used | C12: Current net ASP adjusted by planned ASP change. Compare achieved GM / OM to the target margin. Competitor inputs are context only.
A15: Decision logic
A16: Beat competition | B16: Green | C16: Feasible target COGS is at or below allowable target COGS and at or below competitor COGS.
A17: Margin improvement | B17: Green | C17: Achieved GM or OM at feasible cost meets or exceeds the selected target margin.
A18: Yellow | B18: Near miss | C18: Within ~5 percentage points of margin target, or meets only one of the two competition conditions.
A19: Red | B19: Miss | C19: Misses the controlling conditions for the selected goal type.
A22: Acronyms
A23: COGS | B23: Cost of Goods Sold
A24: GM | B24: Gross Margin
A25: OM | B25: Operating Margin
A26: ASP | B26: Average Selling Price
A27: SG&A | B27: Selling, General & Administrative
A28: BOM | B28: Bill of Materials
A29: OH | B29: Overhead
A30: VE | B30: Value Engineering
A32: Note | B32: Waterfall view removed to keep the tool simpler and reduce confusion.
A44: Tool assessment
A45: This tool is appropriate for target COGS setting on refresh, feature-add, and margin-improvement programs because it combines market price logic, margin logic, current cost structure, feasible cost-down planning, and action tracking in one workflow.
A46: Its strongest use is to set an initial target COGS, quantify the gap, and manage closure actions. It is especially practical when baseline standard cost and credible reduction levers are available.
A47: For Beat competition mode, competitor COGS is an estimate and should be supported by a documented rationale. It is a directional benchmark, not a precise source of truth.
A48: For organization-wide governance, pair this workbook with a simple assumption review: price basis owner, competitor benchmark source, baseline cost date, and action-owner accountability.
A50: Action Maturity Level
A51: Idea | B51: Early concept. Not yet validated.
A52: Scoping | B52: Being assessed for feasibility, timing, or savings.
A53: Validated | B53: Savings logic and technical path are validated.
A54: Committed | B54: Approved and planned for execution.
A55: Implemented | B55: Action already executed; savings should move into actuals.

Sheet Help
A1: Help / User Guide – Target Costing Calculator
A2: Use this tab as the in-workbook guide for the Calculator Form, Action Tracker, and Sensitivity tabs.
A4: 1. Purpose of the Workbook
A5: Step | B5: Area | C5: What it does | D5: Guidance
A6: 1 | B6: Workbook purpose | C6: This workbook helps set and manage target COGS for refresh, feature-add, margin improvement, or competitive repositioning programs. | D6: Use it to connect pricing, margin, baseline cost, cost-down targets, and action closure in one workflow.
A7: 2 | B7: Tabs included | C7: Calculator Form = main working sheet. Action Tracker = savings actions and maturity. Sensitivity = scenario analysis for ASP, margin, and volume. | D7: Use Calculator Form first, then Action Tracker, then Sensitivity.
A8: 2. Calculator Form – How to use it
A9: Step | B9: Section / Field | C9: Meaning | D9: Recommended use
A10: 1 | B10: Goal type | C10: Choose Beat competition or Margin improvement. | D10: Beat competition = competitor cost position matters. Margin improvement = achieved GM/OM vs target matters.
A11: 2 | B11: Competition ASP (best estimate) | C11: Estimated competitor market selling price / net ASP. | D11: Use for market context. Keep the basis documented.
A12: 3 | B12: Competition COGS (best estimate) | C12: Estimated competitor cost position. | D12: Use only as a directional benchmark; it is not a precise fact.
A13: 4 | B13: Current list ASP | C13: Your current list ASP before discounts, rebates, and credits. | D13: Use the current commercial baseline.
A14: 5 | B14: Avg discount %, rebate %, credits % | C14: Price waterfall assumptions used to derive current net ASP. | D14: Use historical realized values, not aspiration.
A15: 6 | B15: Current Net ASP | C15: Calculated realized ASP after deductions. | D15: Do not overwrite; this is formula-driven.
A16: 7 | B16: Planned ASP change % | C16: Used in Margin improvement mode to model a refresh price move. | D16: Keep conservative unless there is strong commercial support.
A17: 8 | B17: Target selling price used | C17: Price basis the model uses for target-cost math. | D17: Beat competition = competition ASP. Margin improvement = current net ASP adjusted by planned ASP change.
A18: 9 | B18: Corporate margin type | C18: Select GM or OM as the controlling metric. | D18: Use GM for typical refresh programs. Use OM when SG&A / support burden changes materially.
A19: 10 | B19: Corporate target margin % | C19: Required target GM% or OM%. | D19: This is the main profit requirement input.
A20: 11 | B20: SG&A per unit (OM only) | C20: Selling, general and administrative cost per unit. | D20: Only relevant when OM is selected.
... A24: 15 | B24: Final allowable target COGS | C24: Target COGS ceiling after buffer. | D24: This is the core target-cost output used by the dashboard.
A25: 3. Baseline Current Product COGS Split
A26: A | B26: Cost element | C26: Meaning | D26: Guidance
A27: 1 | B27: BOM | C27: Current baseline bill of materials cost per unit. | D27: Use latest standard cost / should-cost / actual roll-up.
A28: 2 | B28: Direct Labor | C28: Current direct labor cost per unit. | D28: Use the current manufacturing assumption.
A29: 3 | B29: Variable OH | C29: Current variable overhead per unit. | D29: Include costs that vary directly with production.
A30: 4 | B30: Fixed OH | C30: Current fixed overhead cost per unit. | D30: Use current absorbed fixed overhead per unit.
A31: 5 | B31: Freight / Duty | C31: Current logistics, freight, tariffs, and duty per unit. | D31: Use the current landed-cost basis.
A32: 6 | B32: Warranty / Service | C32: Current warranty or service reserve per unit. | D32: Use a realistic current reserve, not zero by default.
A33: 7 | B33: Other | C33: Any remaining current COGS items not captured above. | D33: Use sparingly and document what is included.
A34: 8 | B34: Baseline Total COGS | C34: Total current product COGS. | D34: This is the baseline reference for the cost-down plan.
A35: 4. Desired COGS Reduction by Cost Element
A36: A | B36: Field | C36: Meaning | D36: Guidance
A37: 1 | B37: Reduction % | C37: Enter the expected reduction versus the baseline cost element. | D37: Enter only realistic, supportable savings assumptions.
A38: 2 | B38: Target cost / unit | C38: Calculated cost for each element after the reduction. | D38: Formula-driven.
A39: 3 | B39: Feasible target COGS from category reductions | C39: Total feasible refreshed-product COGS after applying all cost-element reductions. | D39: This is the model's feasible cost outcome before considering action-tracker maturity separately.
A40: 5. Decision Dashboard
A41: A | B41: Output | C41: What it tells you | D41: How to interpret
A42: 1 | B42: Price basis used | C42: The selling price basis used in target-cost math. | D42: Check this first to confirm the model is anchored correctly.
A43: 2 | B43: Final allowable target COGS | C43: The target COGS ceiling after buffer. | D43: This is the main target to beat.
A44: 3 | B44: Feasible target COGS | C44: The cost outcome based on your entered cost reductions. | D44: Compare this directly against Final allowable target COGS.
A45: 4 | B45: Competitor COGS | C45: Competitor benchmark cost, shown only in Beat competition mode. | D45: Use only as directional market comparison.
A46: 5 | B46: Gap to target COGS | C46: Positive means feasible COGS is still above target. | D46: This drives Required cost-down to target.
A47: 6 | B47: Gap vs competitor COGS | C47: Positive means feasible COGS is still above competitor COGS. | D47: Relevant only in Beat competition mode.
A48: 7 | B48: Achieved GM / Achieved OM | C48: Margin outcome at feasible cost. | D48: In Margin improvement mode, these are the key pass / fail checks.
A49: 8 | B49: Price uplift needed to hit target | C49: How much price would need to increase if cost cannot be reduced enough. | D49: Use as a decision-support output, not a default answer.
A50: 9 | B50: Required cost-down to target | C50: How much more cost needs to come out to hit target. | D50: This cell is color-highlighted by decision status.
A51: 10 | B51: Identified savings from Action Tracker | C51: Expected savings currently identified in the tracker. | D51: Pulled directly from the Action Tracker summary.
A52: 11 | B52: Remaining savings gap after tracker | C52: How much gap still remains after identified savings are considered. | D52: This is the remaining closure challenge.
... A54: 13 | B54: Recommended action | C54: Suggested next step based on the decision status. | D54: Use as the narrative prompt for program reviews.
A55: 6. Action Tracker Tab
A56: A | B56: Field | C56: Meaning | D56: Guidance
A57: 1 | B57: Delta reduction required | C57: Required cost-down pulled from the dashboard. | D57: This is the gap the tracker is trying to close.
A58: 2 | B58: Savings identified so far | C58: Total expected savings from all action lines. | D58: Pulled from the bottom summary of the tracker.
A59: 3 | B59: Remaining gap | C59: Gap still open after identified savings are applied. | D59: Calculated as MAX(0, required gap - MIN(required gap, identified savings)).
A60: 4 | B60: Applied savings capped at gap | C60: Savings counted toward closure, capped to avoid overstating closure. | D60: This prevents savings from exceeding the required gap.
A61: 5 | B61: Action | C61: Name of the cost-down action. | D61: Use specific action wording, not generic labels.
A62: 6 | B62: Owner | C62: Responsible function or person. | D62: Every action should have one accountable owner.
A63: 7 | B63: Subsystem / Cost bucket | C63: Where the action applies. | D63: Use BOM, Direct Labor, Variable OH, Fixed OH, Freight/Warranty/Other as applicable.
A64: 8 | B64: Commitment | C64: Committed or Opportunity. | D64: Committed = approved/expected. Opportunity = not yet fully secured.
A65: 9 | B65: Timing | C65: Expected landing period. | D65: Use for action sequencing.
A66: 10 | B66: Maturity level | C66: Idea, Scoping, Validated, Committed, Implemented. | D66: Use this to judge savings credibility.
A67: 11 | B67: Savings $/unit | C67: Nominal savings for the action. | D67: Enter per-unit value.
... A69: 13 | B69: Weighted savings | C69: Savings multiplied by probability. | D69: Formula-driven.
A70: 7. Sensitivity Tab
A71: A | B71: Area | C71: Meaning | D71: How to use it
A72: 1 | B72: Top driver block | C72: Shows the base price, margin, margin type, SG&A, annual volume, fixed OH per unit, and competitor COGS context. | D72: Use it to confirm the sensitivity assumptions are tied to the current model.
A73: 2 | B73: Allowable target COGS by ASP x Margin | C73: Shows how allowable target COGS changes as ASP and margin assumptions move. | D73: Use this to test commercial and finance scenarios.
A74: 3 | B74: Feasible COGS and Gap by Volume | C74: Shows the effect of volume on fixed OH absorption and gap to target. | D74: Use this to understand how volume changes affect cost competitiveness.
A75: 4 | B75: Gap vs competitor COGS | C75: Only shown in Beat competition mode. | D75: Use to test whether a different volume improves competitive cost position.
A76: 8. GM vs OM – When to use which
A77: A | B77: Metric | C77: When to use it | D77: Notes
A78: 1 | B78: GM | C78: Use for most refresh or feature-add programs where the business model and SG&A burden are stable. | D78: Best for engineering / sourcing design-to-cost control.
A79: 2 | B79: OM | C79: Use when service model, support burden, channel model, or SG&A per unit changes materially. | D79: Best when full operating profitability is the real governing constraint.
A80: 9. Acronyms
A81: A | B81: Acronym | C81: Meaning
A82: 1 | B82: COGS | C82: Cost of Goods Sold
A83: 2 | B83: GM | C83: Gross Margin
A84: 3 | B84: OM | C84: Operating Margin
A85: 4 | B85: ASP | C85: Average Selling Price
A86: 5 | B86: SG&A | C86: Selling, General & Administrative
A87: 6 | B87: BOM | C87: Bill of Materials
A88: 7 | B88: OH | C88: Overhead
A89: 8 | B89: VE | C89: Value Engineering
A90: 10. Best Practices and Limitations
A91: A | B91: Topic | C91: Description | D91: Recommendation
A92: 1 | B92: Baseline quality | C92: The model is only as good as the baseline cost inputs. | D92: Use the latest validated cost roll-up.
A93: 2 | B93: Competitor COGS | C93: Competitor cost is an estimate, not a verified fact. | D93: Document the benchmark basis externally or in review notes.
A94: 3 | B94: Cost-down realism | C94: Aggressive reductions can make the tool look better than reality. | D94: Enter only supportable reductions and track closure in the Action Tracker.
A95: 4 | B95: Savings governance | C95: Savings should not be counted twice between the cost-reduction section and the tracker. | D95: Use the tracker to manage closure actions, not to override baseline logic.
A96: 5 | B96: Sensitivity use | C96: The Sensitivity tab is for scenario testing, not for replacing the main target-setting logic. | D96: Use it after the main form is complete.
A98: Formatting legend: Yellow = user input | Blue text = editable input | Teal = formula / key output
A100: 11. Section 2A – Baseline Should Cost
A101: 1 | B101: Purpose | C101: Captures what the product should cost structurally at baseline using should-cost logic rather than current actual cost. | D101: Use it to distinguish structural inefficiency from execution shortfall.
A102: 2 | B102: Beat competition context | C102: Should Cost helps judge whether the product can realistically approach competitor-like cost levels. | D102: If Should Cost is above Target COGS, the target may be unrealistic even before execution is considered.
A103: 3 | B103: Margin improvement context | C103: Should Cost helps test whether margin goals are strategically achievable at a structural level. | D103: If Should Cost can meet the margin target but Feasible COGS cannot, the gap is execution-related.
A104: 4 | B104: Dashboard linkage | C104: The Executive Decision Dashboard now compares Baseline, Should Cost, Feasible, and Target together. | D104: Review Gap vs Should, Structural Gap, and Strategic Gap before deciding on actions or target changes.

Sheet RACI
